number_recognizer-0.1.4.dist-info/DESCRIPTION.rst
number_recognizer-0.1.4.dist-info/METADATA
number_recognizer-0.1.4.dist-info/RECORD
number_recognizer-0.1.4.dist-info/WHEEL
number_recognizer-0.1.4.dist-info/entry_points.txt
number_recognizer-0.1.4.dist-info/metadata.json
number_recognizer-0.1.4.dist-info/top_level.txt
recognizer/__init__.py
recognizer/cli.py
recognizer/conv_nn.ckpt
recognizer/conv_nn.ckpt.meta
recognizer/recognizer.py
