Metadata-Version: 2.0
Name: number-recognizer
Version: 0.1.4
Summary: A software for the recognition of handwritten numbers.
Home-page: https://github.com/condereis/number-recognizer
Author: Rafael Lopes Conde dos Reis
Author-email: rafael.lcreis@gmail.com
License: BSD license
Keywords: recognizer
Platform: UNKNOWN
Classifier: Development Status :: 2 - Pre-Alpha
Classifier: Intended Audience :: Developers
Classifier: License :: OSI Approved :: BSD License
Classifier: Natural Language :: English
Classifier: Programming Language :: Python :: 2
Classifier: Programming Language :: Python :: 2.6
Classifier: Programming Language :: Python :: 2.7
Classifier: Programming Language :: Python :: 3
Classifier: Programming Language :: Python :: 3.3
Classifier: Programming Language :: Python :: 3.4
Classifier: Programming Language :: Python :: 3.5
Requires-Dist: Click (>=6.0)
Requires-Dist: numpy
Requires-Dist: pandas
